fds/__init__.py
fds/sdk/__init__.py
fds/sdk/FactSetOptions/__init__.py
fds/sdk/FactSetOptions/api_client.py
fds/sdk/FactSetOptions/configuration.py
fds/sdk/FactSetOptions/exceptions.py
fds/sdk/FactSetOptions/model_utils.py
fds/sdk/FactSetOptions/rest.py
fds/sdk/FactSetOptions/api/__init__.py
fds/sdk/FactSetOptions/api/option_chains__screening_api.py
fds/sdk/FactSetOptions/api/prices__volume_api.py
fds/sdk/FactSetOptions/api/reference_api.py
fds/sdk/FactSetOptions/api/risk_measures_api.py
fds/sdk/FactSetOptions/api/snapshot_api.py
fds/sdk/FactSetOptions/apis/__init__.py
fds/sdk/FactSetOptions/model/__init__.py
fds/sdk/FactSetOptions/model/atm_implied_volatility.py
fds/sdk/FactSetOptions/model/atm_implied_volatility_request.py
fds/sdk/FactSetOptions/model/atm_implied_volatility_response.py
fds/sdk/FactSetOptions/model/calendar.py
fds/sdk/FactSetOptions/model/chains.py
fds/sdk/FactSetOptions/model/chains_request.py
fds/sdk/FactSetOptions/model/chains_response.py
fds/sdk/FactSetOptions/model/error_response.py
fds/sdk/FactSetOptions/model/error_response_sub_errors.py
fds/sdk/FactSetOptions/model/exchange.py
fds/sdk/FactSetOptions/model/exchange_screening_id.py
fds/sdk/FactSetOptions/model/frequency.py
fds/sdk/FactSetOptions/model/greeks.py
fds/sdk/FactSetOptions/model/greeks_request.py
fds/sdk/FactSetOptions/model/greeks_response.py
fds/sdk/FactSetOptions/model/id_type.py
fds/sdk/FactSetOptions/model/implied_volatility.py
fds/sdk/FactSetOptions/model/implied_volatility_request.py
fds/sdk/FactSetOptions/model/implied_volatility_response.py
fds/sdk/FactSetOptions/model/option_ids.py
fds/sdk/FactSetOptions/model/option_screening.py
fds/sdk/FactSetOptions/model/option_screening_request.py
fds/sdk/FactSetOptions/model/option_screening_response.py
fds/sdk/FactSetOptions/model/options_dates.py
fds/sdk/FactSetOptions/model/options_dates_request.py
fds/sdk/FactSetOptions/model/options_dates_response.py
fds/sdk/FactSetOptions/model/options_prices.py
fds.sdk.FactSetOptions-1.0.14.dist-info/LICENSE
fds.sdk.FactSetOptions-1.0.14.dist-info/METADATA
fds.sdk.FactSetOptions-1.0.14.dist-info/WHEEL
fds.sdk.FactSetOptions-1.0.14.dist-info/top_level.txt
fds.sdk.FactSetOptions-1.0.14.dist-info/RECORD
